[{"paths": ["group1-shard1of11", "group1-shard2of11", "group1-shard3of11", "group1-shard4of11", "group1-shard5of11", "group1-shard6of11", "group1-shard7of11", "group1-shard8of11", "group1-shard9of11", "group1-shard10of11", "group1-shard11of11"], "weights": [{"name": "generator/g_d6/conv2d_transpose/output_shape", "shape": [4], "dtype": "int32"}, {"name": "generator/g_d6/w", "shape": [5, 5, 3, 64], "dtype": "float32"}, {"name": "generator/g_d5/conv2d_transpose/output_shape", "shape": [4], "dtype": "int32"}, {"name": "generator/g_d5/w", "shape": [5, 5, 32, 128], "dtype": "float32"}, {"name": "generator/g_d4/conv2d_transpose/output_shape", "shape": [4], "dtype": "int32"}, {"name": "generator/g_d4/w", "shape": [5, 5, 64, 256], "dtype": "float32"}, {"name": "generator/g_d3/w", "shape": [5, 5, 128, 512], "dtype": "float32"}, {"name": "generator/g_d2/w", "shape": [5, 5, 256, 512], "dtype": "float32"}, {"name": "ConstantFolding/generator/dropout/div_recip", "shape": [], "dtype": "float32"}, {"name": "generator/g_d1/w", "shape": [5, 5, 256, 256], "dtype": "float32"}, {"name": "generator/g_e6_conv/w", "shape": [5, 5, 256, 256], "dtype": "float32"}, {"name": "generator/g_e6_conv/biases", "shape": [256], "dtype": "float32"}, {"name": "generator/g_bn_e6/gamma", "shape": [256], "dtype": "float32"}, {"name": "generator/g_bn_e6/beta", "shape": [256], "dtype": "float32"}, {"name": "generator/g_d1/biases", "shape": [256], "dtype": "float32"}, {"name": "generator/g_bn_d1/gamma", "shape": [256], "dtype": "float32"}, {"name": "generator/g_bn_d1/beta", "shape": [256], "dtype": "float32"}, {"name": "generator/g_d1/conv2d_transpose/output_shape", "shape": [4], "dtype": "int32"}, {"name": "generator/g_e5_conv/w", "shape": [5, 5, 256, 256], "dtype": "float32"}, {"name": "generator/g_e5_conv/biases", "shape": [256], "dtype": "float32"}, {"name": "generator/g_bn_e5/gamma", "shape": [256], "dtype": "float32"}, {"name": "generator/g_bn_e5/beta", "shape": [256], "dtype": "float32"}, {"name": "generator/g_d2/biases", "shape": [256], "dtype": "float32"}, {"name": "generator/g_bn_d2/gamma", "shape": [256], "dtype": "float32"}, {"name": "generator/g_bn_d2/beta", "shape": [256], "dtype": "float32"}, {"name": "generator/g_d2/conv2d_transpose/output_shape", "shape": [4], "dtype": "int32"}, {"name": "generator/g_e4_conv/w", "shape": [5, 5, 128, 256], "dtype": "float32"}, {"name": "generator/g_e4_conv/biases", "shape": [256], "dtype": "float32"}, {"name": "generator/g_bn_e4/gamma", "shape": [256], "dtype": "float32"}, {"name": "generator/g_bn_e4/beta", "shape": [256], "dtype": "float32"}, {"name": "generator/g_d3/biases", "shape": [128], "dtype": "float32"}, {"name": "generator/g_bn_d3/gamma", "shape": [128], "dtype": "float32"}, {"name": "generator/g_bn_d3/beta", "shape": [128], "dtype": "float32"}, {"name": "generator/dropout/keep_prob", "shape": [], "dtype": "float32"}, {"name": "generator/g_d3/conv2d_transpose/output_shape", "shape": [4], "dtype": "int32"}, {"name": "generator/g_e3_conv/w", "shape": [5, 5, 64, 128], "dtype": "float32"}, {"name": "generator/g_e3_conv/biases", "shape": [128], "dtype": "float32"}, {"name": "generator/g_bn_e3/gamma", "shape": [128], "dtype": "float32"}, {"name": "generator/g_bn_e3/beta", "shape": [128], "dtype": "float32"}, {"name": "generator/g_d4/biases", "shape": [64], "dtype": "float32"}, {"name": "generator/g_bn_d4/gamma", "shape": [64], "dtype": "float32"}, {"name": "generator/g_bn_d4/beta", "shape": [64], "dtype": "float32"}, {"name": "generator/lrelu_4/alpha", "shape": [], "dtype": "float32"}, {"name": "generator/g_e2_conv/w", "shape": [5, 5, 32, 64], "dtype": "float32"}, {"name": "generator/g_e2_conv/biases", "shape": [64], "dtype": "float32"}, {"name": "generator/g_bn_e2/gamma", "shape": [64], "dtype": "float32"}, {"name": "generator/g_bn_e2/beta", "shape": [64], "dtype": "float32"}, {"name": "generator/g_d5/biases", "shape": [32], "dtype": "float32"}, {"name": "generator/g_bn_d5/gamma", "shape": [32], "dtype": "float32"}, {"name": "generator/g_bn_d5/beta", "shape": [32], "dtype": "float32"}, {"name": "generator/g_bn_e6/Const", "shape": [0], "dtype": "float32"}, {"name": "generator/g_e1_conv/w", "shape": [5, 5, 6, 32], "dtype": "float32"}, {"name": "generator/g_e1_conv/biases", "shape": [32], "dtype": "float32"}, {"name": "generator/concat/axis", "shape": [], "dtype": "int32"}, {"name": "generator/g_d6/biases", "shape": [3], "dtype": "float32"}]}]